{
  "schema_version": 2,
  "revision": 47,
  "project": "tas-kag-t-makas-oyunu-yap",
  "workspace": "workspace/tas-kag-t-makas-oyunu-yap",
  "repo_mode": "per-repo",
  "profile": "LITE",
  "current_phase": "12",
  "status": "running",
  "active_agents": [
    {
      "agent": "code-reviewer",
      "model": "opus",
      "phase": "10",
      "task": "Blind code review (src/+tests diff, docs/03,05,07)",
      "started_at": "2026-07-19T12:08:54Z",
      "last_update": "2026-07-19T12:08:54Z"
    },
    {
      "agent": "devops-engineer",
      "model": "sonnet",
      "phase": "12",
      "task": "Dockerfile + .dockerignore + CI/deploy workflow doğrulama",
      "started_at": "2026-07-19T12:13:44Z",
      "last_update": "2026-07-19T12:13:44Z",
      "via": "inline"
    }
  ],
  "phases": {
    "0": {
      "mode": "CHECKPOINT",
      "status": "done",
      "started_at": "2026-07-19T09:45:00Z",
      "artifacts": [
        "docs/00-refined-brief.md",
        "docs/00-idea.md"
      ],
      "decisions": [
        "DL-00-001"
      ],
      "gate_passed": true,
      "completed_at": "2026-07-19T09:47:00Z",
      "note": "Faz 0 (Fikir/Intake) üretildi — onaylı brief üzerinden; problem/başarı kriterleri birebir aktarıldı. Kapı geçti (structural)."
    },
    "3": {
      "mode": "AUTOPILOT",
      "status": "done",
      "started_at": "2026-07-19T10:06:00Z",
      "gate_passed": true,
      "artifacts": [
        "docs/03-requirements.md"
      ],
      "decisions": [
        "DL-03-001"
      ],
      "completed_at": "2026-07-19T10:10:00Z",
      "note": "6 FR + 8 NFR tanımlandı; açık sorular (web, stateless skor, tema) varsayımla kapatıldı. Kapı geçti (structural)."
    },
    "4": {
      "mode": "AUTOPILOT",
      "status": "done",
      "started_at": "2026-07-19T10:12:00Z",
      "gate_passed": true,
      "artifacts": [
        "docs/04-solution-analysis.md"
      ],
      "decisions": [
        "DL-04-001"
      ],
      "completed_at": "2026-07-19T10:25:00Z",
      "note": "architect (opus) devri: Express+vanilla JS istemci-taraflı mantık kararı. Kapı gecti (structural)."
    },
    "5": {
      "mode": "AUTOPILOT",
      "status": "done",
      "started_at": "2026-07-19T10:27:00Z",
      "gate_passed": true,
      "artifacts": [
        "docs/05-architecture.md"
      ],
      "decisions": [
        "DL-05-001"
      ],
      "completed_at": "2026-07-19T10:35:00Z",
      "note": "architect (opus) devri: Mermaid mimari + NFR eslemesi. Kapi gecti (structural)."
    },
    "6": {
      "mode": "AUTOPILOT",
      "status": "done",
      "started_at": "2026-07-19T10:37:00Z",
      "gate_passed": true,
      "artifacts": [
        "docs/06-uiux/06-uiux.md"
      ],
      "decisions": [
        "DL-06-001"
      ],
      "completed_at": "2026-07-19T10:42:00Z",
      "note": "Emoji-tabanli minimal tek ekran UI. Kapi gecti (structural)."
    },
    "7": {
      "mode": "AUTOPILOT",
      "status": "done",
      "started_at": "2026-07-19T10:37:00Z",
      "gate_passed": true,
      "artifacts": [
        "docs/07-security.md"
      ],
      "decisions": [
        "DL-07-001"
      ],
      "completed_at": "2026-07-19T10:52:00Z",
      "note": "security-reviewer (opus) devri: OWASP 10/10 + STRIDE + SEC-1..9 Faz 9ya devredildi. Kritik risk kabulu yok. Kapi gecti (structural)."
    },
    "8": {
      "mode": "AUTOPILOT",
      "status": "done",
      "started_at": "2026-07-19T10:37:00Z",
      "gate_passed": true,
      "artifacts": [
        "docs/08-plan.md"
      ],
      "decisions": [
        "DL-08-001"
      ],
      "completed_at": "2026-07-19T10:48:00Z",
      "note": "7 task, tek milestone, TDD sirali backlog. Kapi gecti (structural)."
    },
    "9": {
      "mode": "AUTOPILOT",
      "status": "done",
      "started_at": "2026-07-19T10:55:00Z",
      "gate_passed": true,
      "completed_at": "2026-07-19T12:04:31Z",
      "tasks": [
        {
          "title": "Test yaz (game+health)",
          "status": "done"
        },
        {
          "title": "Implement (server/game/UI)",
          "status": "done"
        },
        {
          "title": "npm test yeşil (10/10)",
          "status": "done"
        },
        {
          "title": "DL-09-001 yaz",
          "status": "done"
        },
        {
          "title": "commit (test+feat)",
          "status": "done"
        }
      ]
    },
    "10": {
      "mode": "AUTOPILOT",
      "status": "running",
      "started_at": "2026-07-19T12:08:54Z",
      "tasks": [
        {
          "title": "Blind review (src/+tests, docs/03,05,07)",
          "status": "in_progress"
        },
        {
          "title": "Bulgu tablosu + severity + FR izlenebilirlik",
          "status": "pending"
        },
        {
          "title": "DL-10-001 yaz",
          "status": "pending"
        },
        {
          "title": "docs/10-review/PR-1.md commit",
          "status": "pending"
        }
      ]
    },
    "11": {
      "mode": "AUTOPILOT",
      "status": "done",
      "started_at": "2026-07-19T12:08:54Z",
      "tasks": [
        {
          "title": "test-plan.md yaz (kritik senaryolar)",
          "status": "done"
        },
        {
          "title": "Entegrasyon testleri ekle (tests/)",
          "status": "done"
        },
        {
          "title": "npm test yeşil",
          "status": "done"
        },
        {
          "title": "results.md + DL-11-001",
          "status": "done"
        },
        {
          "title": "commit",
          "status": "in_progress"
        }
      ],
      "gate_passed": true,
      "completed_at": "2026-07-19T12:11:46Z",
      "artifacts": [
        "docs/11-test/test-plan.md",
        "docs/11-test/results.md",
        "tests/integration.test.js"
      ],
      "decisions": [
        "DL-11-001"
      ]
    },
    "12": {
      "mode": "AUTOPILOT",
      "status": "running",
      "started_at": "2026-07-19T12:13:44Z",
      "tasks": [
        {
          "title": "Dockerfile + .dockerignore yaz (TASK-007)",
          "status": "in_progress"
        },
        {
          "title": "docker build + boyut ≤150MB doğrula",
          "status": "pending"
        },
        {
          "title": "container çalıştır + /health doğrula",
          "status": "pending"
        },
        {
          "title": "state.product + DL-12-001",
          "status": "pending"
        },
        {
          "title": "commit",
          "status": "pending"
        }
      ]
    },
    "1-2": {
      "mode": "CHECKPOINT",
      "status": "done",
      "started_at": "2026-07-19T09:50:00Z",
      "artifacts": [
        "docs/01-02-value-feasibility.md"
      ],
      "decisions": [
        "DL-01-001"
      ],
      "gate_passed": true,
      "completed_at": "2026-07-19T10:05:00Z",
      "note": "Faz 1+2 (Değer & Fizibilite) üretildi — GO kararı, 4 KPI, kapı geçti (structural); kullanıcı onayı bekleniyor."
    }
  },
  "feedback_loops": [],
  "pending_human_review": [],
  "history": [
    {
      "event": "project_materialized",
      "detail": "Taslak gerçek projeye dönüştürüldü: repo auto-forge-projects/tas-kag-t-makas-oyunu-yap, workspace/tas-kag-t-makas-oyunu-yap"
    },
    {
      "event": "phase_approved",
      "phase": "0b",
      "detail": "Rafine brief onaylandı (dashboard, 2026-07-19)"
    },
    {
      "event": "phase_started",
      "phase": 0,
      "detail": "Faz 0 (Fikir/Intake) üretimi başladı — girdi: onaylı docs/00-refined-brief.md"
    },
    {
      "at": "2026-07-19T09:40:33.904Z",
      "event": "mode_changed",
      "detail": "AUTOPILOT (aktif+sonrası; fazlar: 0)"
    },
    {
      "event": "phase_completed",
      "phase": 0,
      "detail": "docs/00-idea.md üretildi (business-analyst, inline); kapı geçti (structural)"
    },
    {
      "event": "phase_started",
      "phase": "1-2",
      "detail": "Faz 1+2 (Değer & Fizibilite) üretimi başladı — girdi: docs/00-idea.md"
    },
    {
      "event": "phase_completed",
      "phase": "1-2",
      "detail": "docs/01-02-value-feasibility.md üretildi (business-analyst, inline); GO kararı; kapı geçti (structural); kullanıcı onayı bekleniyor"
    },
    {
      "at": "2026-07-19T10:05:00Z",
      "event": "phase_approved",
      "phase": "1-2",
      "detail": "Faz 1+2 (Değer & Fizibilite) kullanıcı tarafından onaylandı (/pipeline-continue); GO kararı kabul edildi."
    },
    {
      "at": "2026-07-19T10:06:00Z",
      "event": "phase_started",
      "phase": "3",
      "detail": "Faz 3 (Requirement Analizi) üretimi başladı — girdi: docs/00-idea.md, docs/01-02-value-feasibility.md"
    },
    {
      "at": "2026-07-19T09:48:35.168Z",
      "event": "mode_changed",
      "detail": "AUTOPILOT (aktif+sonrası; fazlar: 3)"
    },
    {
      "at": "2026-07-19T10:10:00Z",
      "event": "phase_completed",
      "phase": "3",
      "detail": "docs/03-requirements.md üretildi (business-analyst, inline); kapı geçti (structural); AUTOPILOT → devam"
    },
    {
      "at": "2026-07-19T10:12:00Z",
      "event": "phase_started",
      "phase": "4",
      "detail": "Faz 4 (Cozum Analizi) architect subagenta devredildi - girdi: docs/03-requirements.md (model farki: Opus > oturum Sonnet)"
    },
    {
      "at": "2026-07-19T10:25:00Z",
      "event": "phase_completed",
      "phase": "4",
      "detail": "docs/04-solution-analysis.md uretildi (architect subagent); kapi gecti (structural); AUTOPILOT -> devam"
    },
    {
      "at": "2026-07-19T10:27:00Z",
      "event": "phase_started",
      "phase": "5",
      "detail": "Faz 5 (Mimari Tasarim) architect subagenta devredildi - girdi: docs/03-requirements.md, docs/04-solution-analysis.md"
    },
    {
      "at": "2026-07-19T10:35:00Z",
      "event": "phase_completed",
      "phase": "5",
      "detail": "docs/05-architecture.md uretildi (architect subagent); kapi gecti (structural); AUTOPILOT -> devam. Faz 6/7/8 paralel acilabilir (deps: 5)."
    },
    {
      "at": "2026-07-19T10:37:00Z",
      "event": "phase_started",
      "detail": "Faz 6/7/8 paralel acildi (deps: 5 tamamlandi). Faz 7 security-reviewer subagenta devredildi (zorunlu); Faz 6/8 inline."
    },
    {
      "at": "2026-07-19T10:42:00Z",
      "event": "phase_completed",
      "phase": "6",
      "detail": "docs/06-uiux/06-uiux.md uretildi (developer, inline); kapi gecti (structural)"
    },
    {
      "at": "2026-07-19T10:48:00Z",
      "event": "phase_completed",
      "phase": "8",
      "detail": "docs/08-plan.md uretildi (business-analyst, inline); kapi gecti (structural)"
    },
    {
      "at": "2026-07-19T10:52:00Z",
      "event": "phase_completed",
      "phase": "7",
      "detail": "docs/07-security.md uretildi (security-reviewer subagent); kapi gecti (structural); Faz 6/7/8 uclu paralel tamamlandi -> Faz 9 acilabilir"
    },
    {
      "at": "2026-07-19T10:55:00Z",
      "event": "phase_started",
      "phase": "9",
      "detail": "Faz 9 (Development) basladi - girdi: docs/03,05,07,08. TDD sirasi: game.js -> server.js -> UI"
    },
    {
      "at": "2026-07-19T12:04:31Z",
      "event": "recovered",
      "phase": "9",
      "detail": "Faz 9 kesinti sonrası kurtarıldı: iş listesinden devam (done adımlar diskte doğrulandı, yalnız commit kaldı) → test+feat commit + kapanış. AF-036/038"
    }
  ],
  "budget": {
    "model_calls": {},
    "notes": ""
  },
  "updated_at": "2026-07-19T12:13:44Z",
  "default_mode": "AUTOPILOT"
}
